gfreader/__init__.py
gfreader/base.py
gfreader/ref_adjust.py
gfreader-1.0.5.dist-info/METADATA
gfreader-1.0.5.dist-info/WHEEL
gfreader-1.0.5.dist-info/licenses/LICENSE
gfreader-1.0.5.dist-info/RECORD
