Metadata-Version: 2.4
Name: gfreader
Version: 1.0.5
Summary: Genotype reader of vcf, plink or hmp format files
License-File: LICENSE
Requires-Python: <3.14,>=3.9
Requires-Dist: bed-reader==1.0.5
Requires-Dist: pandas
